structlogger/__init__.py
structlogger-0.1.5.dist-info/LICENSE
structlogger-0.1.5.dist-info/METADATA
structlogger-0.1.5.dist-info/WHEEL
structlogger-0.1.5.dist-info/top_level.txt
structlogger-0.1.5.dist-info/RECORD
