Metadata-Version: 2.1
Name: structlogger
Version: 0.1.5
Summary: Uses structlog to create two loggers, a stdout logger with key-value args and optional colour, and a file logger in JSON format with log-rotation.
Home-page: UNKNOWN
Author: Matt Davis
Author-email: mattdavis90@googlemail.com
License: MIT
Project-URL: homepage, https://github.com/mattdavis90/structlogger
Project-URL: repository, https://github.com/mattdavis90/structlogger
Platform: UNKNOWN
Requires-Python: ==3.*,>=3.6.0
Requires-Dist: python-json-logger (==0.*,>=0.1.9)
Requires-Dist: structlog[dev] (==20.*,>=20.1.0)
